{
  "_description": "T模式配置: long=正T(先买后卖), short=反T(先卖后买). 启动时未设置会提示选择.",
  "_last_updated": "2026-07-15",
  "_update_source": "持仓截图更新",
  "_auto_decision": {
    "date": "2026-07-20",
    "regime": "uni_down",
    "regime_name": "单边下行",
    "z_top3": -1.466,
    "basis_date": "2026-07-20",
    "matrix_mode": "hold",
    "pos_factor": 0.0,
    "reason": "单边下行×冰点→观望不做T(仅恐慌急杀允许极小仓正T)",
    "per_stock": {
      "300153": "hold",
      "300364": "hold",
      "300054": "hold",
      "588170": "hold",
      "600176": "hold",
      "600481": "hold",
      "603667": "hold",
      "000988": "hold",
      "000988_B": "hold"
    },
    "source": "auto_v3.1"
  }
}