{"code": "688102", "name": "陕西斯瑞新材股份", "date": "2026-06-18", "saved_at": "2026-06-18 14:59:49", "row_count": 241, "last_time": "2026-06-18 14:59:00", "last_close": 45.74, "last_vwap": 44.57177622135786, "market_state": "range_bound", "benchmark_code": "sh000688", "benchmark_name": "科创50", "benchmark_state": "range_bound", "benchmark_gate": "neutral", "benchmark_reason": "指数中性", "signal": {"action": "SELL_HIGH", "score": 48, "reasons": ["回吐空间", "MACD拐头", "EMA转弱", "日线过热"], "entry_kind": "sell_high"}, "daily_context": {"daily_status": "ok", "daily_reason": "", "daily_asof": "2026-06-18", "daily_price_ref": 45.34, "daily_prev_close": 41.82, "daily_day_ret": 0.07771401243424199, "daily_ma5": 41.834, "daily_ma5_slope": 0.097832362357634, "daily_above_ma5": true, "daily_ma5_gap": 0.08380742936367548, "daily_ma5_state": "above_ma5_trend", "daily_ma10": 39.97, "daily_ma20": 38.568, "daily_ma30": 40.22566666666667, "daily_ma60": 38.824333333333335, "daily_ma10_slope": 0.0872048743335873, "daily_ma20_slope": 0.0029645810578872735, "daily_ma30_slope": 0.002400571485530309, "daily_ma60_slope": 0.008563956911779838, "daily_trend_bg": "uptrend", "daily_gate": "overheat", "daily_support_name": "", "daily_support_level": 0.0, "daily_support_gap": 0.0, "daily_near_support": false, "daily_pullback_support": false, "daily_breakdown_risk": false, "daily_hard_breakdown": false, "daily_overheated": true, "daily_ma_clustered": true, "daily_bull_aligned": false}, "bars": [{"time": "2026-06-18 09:30:00", "open": 41.0, "high": 41.0, "low": 41.0, "close": 41.0, "volume": 187964.0, "amount": 7706524.0}, {"time": "2026-06-18 09:31:00", "open": 40.6, "high": 40.6, "low": 40.6, "close": 40.6, "volume": 660577.0, "amount": 26957453.0}, {"time": "2026-06-18 09:32:00", "open": 41.5, "high": 41.5, "low": 41.5, "close": 41.5, "volume": 1444104.0, "amount": 58879754.0}, {"time": "2026-06-18 09:33:00", "open": 41.35, "high": 41.35, "low": 41.35, "close": 41.35, "volume": 1743861.0, "amount": 71274077.0}, {"time": "2026-06-18 09:34:00", "open": 41.8, "high": 41.8, "low": 41.8, "close": 41.8, "volume": 2127856.0, "amount": 87247270.0}, {"time": "2026-06-18 09:35:00", "open": 41.85, "high": 41.85, "low": 41.85, "close": 41.85, "volume": 2476231.0, "amount": 101802418.0}, {"time": "2026-06-18 09:36:00", "open": 41.86, "high": 41.86, "low": 41.86, "close": 41.86, "volume": 2813898.0, "amount": 115917757.0}, {"time": "2026-06-18 09:37:00", "open": 42.19, "high": 42.19, "low": 42.19, "close": 42.19, "volume": 3252320.0, "amount": 134370100.0}, {"time": "2026-06-18 09:38:00", "open": 42.04, "high": 42.04, "low": 42.04, "close": 42.04, "volume": 3636053.0, "amount": 150481228.0}, {"time": "2026-06-18 09:39:00", "open": 42.54, "high": 42.54, "low": 42.54, "close": 42.54, "volume": 4003643.0, "amount": 166014945.0}, {"time": "2026-06-18 09:40:00", "open": 42.85, "high": 42.85, "low": 42.85, "close": 42.85, "volume": 4621121.0, "amount": 192418808.0}, {"time": "2026-06-18 09:41:00", "open": 42.89, "high": 42.89, "low": 42.89, "close": 42.89, "volume": 5208255.0, "amount": 217638479.0}, {"time": "2026-06-18 09:42:00", "open": 42.41, "high": 42.41, "low": 42.41, "close": 42.41, "volume": 5393441.0, "amount": 225524739.0}, {"time": "2026-06-18 09:43:00", "open": 42.3, "high": 42.3, "low": 42.3, "close": 42.3, "volume": 5726362.0, "amount": 239650864.0}, {"time": "2026-06-18 09:44:00", "open": 42.46, "high": 42.46, "low": 42.46, "close": 42.46, "volume": 5954403.0, "amount": 249303244.0}, {"time": "2026-06-18 09:45:00", "open": 42.29, "high": 42.29, "low": 42.29, "close": 42.29, "volume": 6152949.0, "amount": 257722425.0}, {"time": "2026-06-18 09:46:00", "open": 42.1, "high": 42.1, "low": 42.1, "close": 42.1, "volume": 6366449.0, "amount": 266739384.0}, {"time": "2026-06-18 09:47:00", "open": 42.13, "high": 42.13, "low": 42.13, "close": 42.13, "volume": 6575325.0, "amount": 275539309.0}, {"time": "2026-06-18 09:48:00", "open": 42.12, "high": 42.12, "low": 42.12, "close": 42.12, "volume": 6802549.0, "amount": 285101735.0}, {"time": "2026-06-18 09:49:00", "open": 42.41, "high": 42.41, "low": 42.41, "close": 42.41, "volume": 6977294.0, "amount": 292499018.0}, {"time": "2026-06-18 09:50:00", "open": 42.69, "high": 42.69, "low": 42.69, "close": 42.69, "volume": 7233140.0, "amount": 303401806.0}, {"time": "2026-06-18 09:51:00", "open": 42.55, "high": 42.55, "low": 42.55, "close": 42.55, "volume": 7453644.0, "amount": 312820920.0}, {"time": "2026-06-18 09:52:00", "open": 42.97, "high": 42.97, "low": 42.97, "close": 42.97, "volume": 7769490.0, "amount": 326311861.0}, {"time": "2026-06-18 09:53:00", "open": 42.81, "high": 42.81, "low": 42.81, "close": 42.81, "volume": 7916106.0, "amount": 332597759.0}, {"time": "2026-06-18 09:54:00", "open": 42.66, "high": 42.66, "low": 42.66, "close": 42.66, "volume": 8061655.0, "amount": 338823517.0}, {"time": "2026-06-18 09:55:00", "open": 43.0, "high": 43.0, "low": 43.0, "close": 43.0, "volume": 8765771.0, "amount": 369037246.0}, {"time": "2026-06-18 09:56:00", "open": 43.32, "high": 43.32, "low": 43.32, "close": 43.32, "volume": 9448215.0, "amount": 398486728.0}, {"time": "2026-06-18 09:57:00", "open": 43.75, "high": 43.75, "low": 43.75, "close": 43.75, "volume": 10302775.0, "amount": 435666182.0}, {"time": "2026-06-18 09:58:00", "open": 43.52, "high": 43.52, "low": 43.52, "close": 43.52, "volume": 10894064.0, "amount": 461574307.0}, {"time": "2026-06-18 09:59:00", "open": 43.43, "high": 43.43, "low": 43.43, "close": 43.43, "volume": 11172492.0, "amount": 473690405.0}, {"time": "2026-06-18 10:00:00", "open": 43.39, "high": 43.39, "low": 43.39, "close": 43.39, "volume": 11407394.0, "amount": 483875261.0}, {"time": "2026-06-18 10:01:00", "open": 43.42, "high": 43.42, "low": 43.42, "close": 43.42, "volume": 11766821.0, "amount": 499489975.0}, {"time": "2026-06-18 10:02:00", "open": 43.66, "high": 43.66, "low": 43.66, "close": 43.66, "volume": 12081546.0, "amount": 513138413.0}, {"time": "2026-06-18 10:03:00", "open": 43.55, "high": 43.55, "low": 43.55, "close": 43.55, "volume": 12473642.0, "amount": 530218462.0}, {"time": "2026-06-18 10:04:00", "open": 43.45, "high": 43.45, "low": 43.45, "close": 43.45, "volume": 12889998.0, "amount": 548373193.0}, {"time": "2026-06-18 10:05:00", "open": 43.45, "high": 43.45, "low": 43.45, "close": 43.45, "volume": 13184832.0, "amount": 561180612.0}, {"time": "2026-06-18 10:06:00", "open": 43.7, "high": 43.7, "low": 43.7, "close": 43.7, "volume": 13457774.0, "amount": 573072953.0}, {"time": "2026-06-18 10:07:00", "open": 44.11, "high": 44.11, "low": 44.11, "close": 44.11, "volume": 14606543.0, "amount": 623535474.0}, {"time": "2026-06-18 10:08:00", "open": 44.4, "high": 44.4, "low": 44.4, "close": 44.4, "volume": 15379528.0, "amount": 657846624.0}, {"time": "2026-06-18 10:09:00", "open": 44.09, "high": 44.09, "low": 44.09, "close": 44.09, "volume": 15807092.0, "amount": 676804730.0}, {"time": "2026-06-18 10:10:00", "open": 44.23, "high": 44.23, "low": 44.23, "close": 44.23, "volume": 16134770.0, "amount": 691301469.0}, {"time": "2026-06-18 10:11:00", "open": 44.0, "high": 44.0, "low": 44.0, "close": 44.0, "volume": 16505645.0, "amount": 707643198.0}, {"time": "2026-06-18 10:12:00", "open": 44.27, "high": 44.27, "low": 44.27, "close": 44.27, "volume": 16783247.0, "amount": 719871972.0}, {"time": "2026-06-18 10:13:00", "open": 44.32, "high": 44.32, "low": 44.32, "close": 44.32, "volume": 17153426.0, "amount": 736295559.0}, {"time": "2026-06-18 10:14:00", "open": 44.74, "high": 44.74, "low": 44.74, "close": 44.74, "volume": 17947393.0, "amount": 771719107.0}, {"time": "2026-06-18 10:15:00", "open": 44.67, "high": 44.67, "low": 44.67, "close": 44.67, "volume": 18258338.0, "amount": 785573105.0}, {"time": "2026-06-18 10:16:00", "open": 44.41, "high": 44.41, "low": 44.41, "close": 44.41, "volume": 18472617.0, "amount": 795150871.0}, {"time": "2026-06-18 10:17:00", "open": 44.36, "high": 44.36, "low": 44.36, "close": 44.36, "volume": 18666104.0, "amount": 803755967.0}, {"time": "2026-06-18 10:18:00", "open": 44.21, "high": 44.21, "low": 44.21, "close": 44.21, "volume": 18791737.0, "amount": 809321342.0}, {"time": "2026-06-18 10:19:00", "open": 44.07, "high": 44.07, "low": 44.07, "close": 44.07, "volume": 19187372.0, "amount": 826815338.0}, {"time": "2026-06-18 10:20:00", "open": 44.0, "high": 44.0, "low": 44.0, "close": 44.0, "volume": 19346516.0, "amount": 833819897.0}, {"time": "2026-06-18 10:21:00", "open": 44.12, "high": 44.12, "low": 44.12, "close": 44.12, "volume": 19665413.0, "amount": 847845681.0}, {"time": "2026-06-18 10:22:00", "open": 44.25, "high": 44.25, "low": 44.25, "close": 44.25, "volume": 19805497.0, "amount": 854036069.0}, {"time": "2026-06-18 10:23:00", "open": 43.99, "high": 43.99, "low": 43.99, "close": 43.99, "volume": 19938306.0, "amount": 859886910.0}, {"time": "2026-06-18 10:24:00", "open": 44.61, "high": 44.61, "low": 44.61, "close": 44.61, "volume": 20289382.0, "amount": 875419591.0}, {"time": "2026-06-18 10:25:00", "open": 45.42, "high": 45.42, "low": 45.42, "close": 45.42, "volume": 21984001.0, "amount": 951596249.0}, {"time": "2026-06-18 10:26:00", "open": 45.02, "high": 45.02, "low": 45.02, "close": 45.02, "volume": 22557828.0, "amount": 977583623.0}, {"time": "2026-06-18 10:27:00", "open": 44.88, "high": 44.88, "low": 44.88, "close": 44.88, "volume": 22790160.0, "amount": 988028302.0}, {"time": "2026-06-18 10:28:00", "open": 45.11, "high": 45.11, "low": 45.11, "close": 45.11, "volume": 23161454.0, "amount": 1004728266.0}, {"time": "2026-06-18 10:29:00", "open": 44.89, "high": 44.89, "low": 44.89, "close": 44.89, "volume": 23470082.0, "amount": 1018631057.0}, {"time": "2026-06-18 10:30:00", "open": 44.82, "high": 44.82, "low": 44.82, "close": 44.82, "volume": 23663887.0, "amount": 1027324072.0}, {"time": "2026-06-18 10:31:00", "open": 44.82, "high": 44.82, "low": 44.82, "close": 44.82, "volume": 23899903.0, "amount": 1037907266.0}, {"time": "2026-06-18 10:32:00", "open": 44.91, "high": 44.91, "low": 44.91, "close": 44.91, "volume": 24103637.0, "amount": 1047065534.0}, {"time": "2026-06-18 10:33:00", "open": 44.83, "high": 44.83, "low": 44.83, "close": 44.83, "volume": 24287553.0, "amount": 1055342573.0}, {"time": "2026-06-18 10:34:00", "open": 44.77, "high": 44.77, "low": 44.77, "close": 44.77, "volume": 24510013.0, "amount": 1065310831.0}, {"time": "2026-06-18 10:35:00", "open": 44.71, "high": 44.71, "low": 44.71, "close": 44.71, "volume": 24654580.0, "amount": 1071790340.0}, {"time": "2026-06-18 10:36:00", "open": 44.55, "high": 44.55, "low": 44.55, "close": 44.55, "volume": 24803831.0, "amount": 1078453834.0}, {"time": "2026-06-18 10:37:00", "open": 44.38, "high": 44.38, "low": 44.38, "close": 44.38, "volume": 25002039.0, "amount": 1087262527.0}, {"time": "2026-06-18 10:38:00", "open": 44.29, "high": 44.29, "low": 44.29, "close": 44.29, "volume": 25146622.0, "amount": 1093669550.0}, {"time": "2026-06-18 10:39:00", "open": 44.46, "high": 44.46, "low": 44.46, "close": 44.46, "volume": 25226991.0, "amount": 1097239316.0}, {"time": "2026-06-18 10:40:00", "open": 44.81, "high": 44.81, "low": 44.81, "close": 44.81, "volume": 25387601.0, "amount": 1104404746.0}, {"time": "2026-06-18 10:41:00", "open": 45.19, "high": 45.19, "low": 45.19, "close": 45.19, "volume": 25647268.0, "amount": 1116086830.0}, {"time": "2026-06-18 10:42:00", "open": 45.14, "high": 45.14, "low": 45.14, "close": 45.14, "volume": 25818435.0, "amount": 1123816101.0}, {"time": "2026-06-18 10:43:00", "open": 45.26, "high": 45.26, "low": 45.26, "close": 45.26, "volume": 26098297.0, "amount": 1136472325.0}, {"time": "2026-06-18 10:44:00", "open": 44.89, "high": 44.89, "low": 44.89, "close": 44.89, "volume": 26201785.0, "amount": 1141144712.0}, {"time": "2026-06-18 10:45:00", "open": 44.81, "high": 44.81, "low": 44.81, "close": 44.81, "volume": 26344735.0, "amount": 1147557450.0}, {"time": "2026-06-18 10:46:00", "open": 44.89, "high": 44.89, "low": 44.89, "close": 44.89, "volume": 26444825.0, "amount": 1152045314.0}, {"time": "2026-06-18 10:47:00", "open": 44.85, "high": 44.85, "low": 44.85, "close": 44.85, "volume": 26539438.0, "amount": 1156297058.0}, {"time": "2026-06-18 10:48:00", "open": 44.47, "high": 44.47, "low": 44.47, "close": 44.47, "volume": 26661963.0, "amount": 1161756486.0}, {"time": "2026-06-18 10:49:00", "open": 44.76, "high": 44.76, "low": 44.76, "close": 44.76, "volume": 26792715.0, "amount": 1167582917.0}, {"time": "2026-06-18 10:50:00", "open": 44.52, "high": 44.52, "low": 44.52, "close": 44.52, "volume": 26838309.0, "amount": 1169617280.0}, {"time": "2026-06-18 10:51:00", "open": 44.49, "high": 44.49, "low": 44.49, "close": 44.49, "volume": 26986489.0, "amount": 1176208289.0}, {"time": "2026-06-18 10:52:00", "open": 44.61, "high": 44.61, "low": 44.61, "close": 44.61, "volume": 27138886.0, "amount": 1182989778.0}, {"time": "2026-06-18 10:53:00", "open": 44.58, "high": 44.58, "low": 44.58, "close": 44.58, "volume": 27187441.0, "amount": 1185154744.0}, {"time": "2026-06-18 10:54:00", "open": 44.99, "high": 44.99, "low": 44.99, "close": 44.99, "volume": 27316763.0, "amount": 1190970195.0}, {"time": "2026-06-18 10:55:00", "open": 44.78, "high": 44.78, "low": 44.78, "close": 44.78, "volume": 27378610.0, "amount": 1193739617.0}, {"time": "2026-06-18 10:56:00", "open": 45.18, "high": 45.18, "low": 45.18, "close": 45.18, "volume": 27593089.0, "amount": 1203382166.0}, {"time": "2026-06-18 10:57:00", "open": 45.08, "high": 45.08, "low": 45.08, "close": 45.08, "volume": 27857934.0, "amount": 1215350459.0}, {"time": "2026-06-18 10:58:00", "open": 45.0, "high": 45.0, "low": 45.0, "close": 45.0, "volume": 27916892.0, "amount": 1218007653.0}, {"time": "2026-06-18 10:59:00", "open": 44.77, "high": 44.77, "low": 44.77, "close": 44.77, "volume": 27946394.0, "amount": 1219328871.0}, {"time": "2026-06-18 11:00:00", "open": 44.61, "high": 44.61, "low": 44.61, "close": 44.61, "volume": 28007050.0, "amount": 1222039266.0}, {"time": "2026-06-18 11:01:00", "open": 44.64, "high": 44.64, "low": 44.64, "close": 44.64, "volume": 28065611.0, "amount": 1224652990.0}, {"time": "2026-06-18 11:02:00", "open": 44.61, "high": 44.61, "low": 44.61, "close": 44.61, "volume": 28118125.0, "amount": 1226998484.0}, {"time": "2026-06-18 11:03:00", "open": 44.45, "high": 44.45, "low": 44.45, "close": 44.45, "volume": 28224694.0, "amount": 1231744620.0}, {"time": "2026-06-18 11:04:00", "open": 44.38, "high": 44.38, "low": 44.38, "close": 44.38, "volume": 28433504.0, "amount": 1241015183.0}, {"time": "2026-06-18 11:05:00", "open": 44.44, "high": 44.44, "low": 44.44, "close": 44.44, "volume": 28550944.0, "amount": 1246233819.0}, {"time": "2026-06-18 11:06:00", "open": 44.45, "high": 44.45, "low": 44.45, "close": 44.45, "volume": 28734977.0, "amount": 1254397144.0}, {"time": "2026-06-18 11:07:00", "open": 44.35, "high": 44.35, "low": 44.35, "close": 44.35, "volume": 28814812.0, "amount": 1257941249.0}, {"time": "2026-06-18 11:08:00", "open": 44.35, "high": 44.35, "low": 44.35, "close": 44.35, "volume": 28893154.0, "amount": 1261411236.0}, {"time": "2026-06-18 11:09:00", "open": 44.28, "high": 44.28, "low": 44.28, "close": 44.28, "volume": 28956215.0, "amount": 1264207245.0}, {"time": "2026-06-18 11:10:00", "open": 44.2, "high": 44.2, "low": 44.2, "close": 44.2, "volume": 29079719.0, "amount": 1269666335.0}, {"time": "2026-06-18 11:11:00", "open": 44.33, "high": 44.33, "low": 44.33, "close": 44.33, "volume": 29132573.0, "amount": 1272006205.0}, {"time": "2026-06-18 11:12:00", "open": 44.29, "high": 44.29, "low": 44.29, "close": 44.29, "volume": 29177482.0, "amount": 1273996385.0}, {"time": "2026-06-18 11:13:00", "open": 44.01, "high": 44.01, "low": 44.01, "close": 44.01, "volume": 29274236.0, "amount": 1278264880.0}, {"time": "2026-06-18 11:14:00", "open": 44.0, "high": 44.0, "low": 44.0, "close": 44.0, "volume": 29491048.0, "amount": 1287806471.0}, {"time": "2026-06-18 11:15:00", "open": 44.02, "high": 44.02, "low": 44.02, "close": 44.02, "volume": 29625009.0, "amount": 1293700580.0}, {"time": "2026-06-18 11:16:00", "open": 44.02, "high": 44.02, "low": 44.02, "close": 44.02, "volume": 29755834.0, "amount": 1299468098.0}, {"time": "2026-06-18 11:17:00", "open": 44.32, "high": 44.32, "low": 44.32, "close": 44.32, "volume": 29823534.0, "amount": 1302461692.0}, {"time": "2026-06-18 11:18:00", "open": 44.25, "high": 44.25, "low": 44.25, "close": 44.25, "volume": 29923165.0, "amount": 1306869772.0}, {"time": "2026-06-18 11:19:00", "open": 44.35, "high": 44.35, "low": 44.35, "close": 44.35, "volume": 29968216.0, "amount": 1308867856.0}, {"time": "2026-06-18 11:20:00", "open": 44.43, "high": 44.43, "low": 44.43, "close": 44.43, "volume": 30098936.0, "amount": 1314660126.0}, {"time": "2026-06-18 11:21:00", "open": 44.48, "high": 44.48, "low": 44.48, "close": 44.48, "volume": 30252635.0, "amount": 1321489399.0}, {"time": "2026-06-18 11:22:00", "open": 44.69, "high": 44.69, "low": 44.69, "close": 44.69, "volume": 30354236.0, "amount": 1326014068.0}, {"time": "2026-06-18 11:23:00", "open": 44.65, "high": 44.65, "low": 44.65, "close": 44.65, "volume": 30483056.0, "amount": 1331767913.0}, {"time": "2026-06-18 11:24:00", "open": 44.71, "high": 44.71, "low": 44.71, "close": 44.71, "volume": 30589271.0, "amount": 1336506803.0}, {"time": "2026-06-18 11:25:00", "open": 44.58, "high": 44.58, "low": 44.58, "close": 44.58, "volume": 30668389.0, "amount": 1340039723.0}, {"time": "2026-06-18 11:26:00", "open": 44.4, "high": 44.4, "low": 44.4, "close": 44.4, "volume": 30701078.0, "amount": 1341493382.0}, {"time": "2026-06-18 11:27:00", "open": 44.31, "high": 44.31, "low": 44.31, "close": 44.31, "volume": 30766722.0, "amount": 1344403007.0}, {"time": "2026-06-18 11:28:00", "open": 44.3, "high": 44.3, "low": 44.3, "close": 44.3, "volume": 30827488.0, "amount": 1347095627.0}, {"time": "2026-06-18 11:29:00", "open": 44.44, "high": 44.44, "low": 44.44, "close": 44.44, "volume": 30872753.0, "amount": 1349104895.0}, {"time": "2026-06-18 11:30:00", "open": 44.36, "high": 44.36, "low": 44.36, "close": 44.36, "volume": 30884662.0, "amount": 1349633815.0}, {"time": "2026-06-18 13:00:00", "open": 44.36, "high": 44.36, "low": 44.36, "close": 44.36, "volume": 30884662.0, "amount": 1349633815.0}, {"time": "2026-06-18 13:01:00", "open": 44.2, "high": 44.2, "low": 44.2, "close": 44.2, "volume": 31107616.0, "amount": 1359513080.0}, {"time": "2026-06-18 13:02:00", "open": 44.43, "high": 44.43, "low": 44.43, "close": 44.43, "volume": 31166118.0, "amount": 1362104924.0}, {"time": "2026-06-18 13:03:00", "open": 44.3, "high": 44.3, "low": 44.3, "close": 44.3, "volume": 31219042.0, "amount": 1364452483.0}, {"time": "2026-06-18 13:04:00", "open": 44.16, "high": 44.16, "low": 44.16, "close": 44.16, "volume": 31238344.0, "amount": 1365306428.0}, {"time": "2026-06-18 13:05:00", "open": 44.15, "high": 44.15, "low": 44.15, "close": 44.15, "volume": 31277846.0, "amount": 1367051120.0}, {"time": "2026-06-18 13:06:00", "open": 44.25, "high": 44.25, "low": 44.25, "close": 44.25, "volume": 31330446.0, "amount": 1369372590.0}, {"time": "2026-06-18 13:07:00", "open": 44.21, "high": 44.21, "low": 44.21, "close": 44.21, "volume": 31383070.0, "amount": 1371699704.0}, {"time": "2026-06-18 13:08:00", "open": 44.25, "high": 44.25, "low": 44.25, "close": 44.25, "volume": 31429717.0, "amount": 1373758691.0}, {"time": "2026-06-18 13:09:00", "open": 44.11, "high": 44.11, "low": 44.11, "close": 44.11, "volume": 31465228.0, "amount": 1375326334.0}, {"time": "2026-06-18 13:10:00", "open": 44.14, "high": 44.14, "low": 44.14, "close": 44.14, "volume": 31527279.0, "amount": 1378064036.0}, {"time": "2026-06-18 13:11:00", "open": 44.23, "high": 44.23, "low": 44.23, "close": 44.23, "volume": 31578477.0, "amount": 1380324163.0}, {"time": "2026-06-18 13:12:00", "open": 44.1, "high": 44.1, "low": 44.1, "close": 44.1, "volume": 31625101.0, "amount": 1382381950.0}, {"time": "2026-06-18 13:13:00", "open": 44.0, "high": 44.0, "low": 44.0, "close": 44.0, "volume": 31740236.0, "amount": 1387449063.0}, {"time": "2026-06-18 13:14:00", "open": 43.99, "high": 43.99, "low": 43.99, "close": 43.99, "volume": 31807957.0, "amount": 1390428639.0}, {"time": "2026-06-18 13:15:00", "open": 44.0, "high": 44.0, "low": 44.0, "close": 44.0, "volume": 31860063.0, "amount": 1392721230.0}, {"time": "2026-06-18 13:16:00", "open": 44.27, "high": 44.27, "low": 44.27, "close": 44.27, "volume": 31964836.0, "amount": 1397339013.0}, {"time": "2026-06-18 13:17:00", "open": 44.27, "high": 44.27, "low": 44.27, "close": 44.27, "volume": 31989489.0, "amount": 1398430536.0}, {"time": "2026-06-18 13:18:00", "open": 44.22, "high": 44.22, "low": 44.22, "close": 44.22, "volume": 32015171.0, "amount": 1399567019.0}, {"time": "2026-06-18 13:19:00", "open": 44.27, "high": 44.27, "low": 44.27, "close": 44.27, "volume": 32042557.0, "amount": 1400778529.0}, {"time": "2026-06-18 13:20:00", "open": 44.26, "high": 44.26, "low": 44.26, "close": 44.26, "volume": 32145875.0, "amount": 1405351079.0}, {"time": "2026-06-18 13:21:00", "open": 44.26, "high": 44.26, "low": 44.26, "close": 44.26, "volume": 32199563.0, "amount": 1407725704.0}, {"time": "2026-06-18 13:22:00", "open": 44.22, "high": 44.22, "low": 44.22, "close": 44.22, "volume": 32217777.0, "amount": 1408532150.0}, {"time": "2026-06-18 13:23:00", "open": 44.2, "high": 44.2, "low": 44.2, "close": 44.2, "volume": 32250675.0, "amount": 1409986132.0}, {"time": "2026-06-18 13:24:00", "open": 44.26, "high": 44.26, "low": 44.26, "close": 44.26, "volume": 32260826.0, "amount": 1410435334.0}, {"time": "2026-06-18 13:25:00", "open": 44.22, "high": 44.22, "low": 44.22, "close": 44.22, "volume": 32293275.0, "amount": 1411871582.0}, {"time": "2026-06-18 13:26:00", "open": 44.27, "high": 44.27, "low": 44.27, "close": 44.27, "volume": 32415124.0, "amount": 1417257001.0}, {"time": "2026-06-18 13:27:00", "open": 44.5, "high": 44.5, "low": 44.5, "close": 44.5, "volume": 32509153.0, "amount": 1421431295.0}, {"time": "2026-06-18 13:28:00", "open": 44.55, "high": 44.55, "low": 44.55, "close": 44.55, "volume": 32554448.0, "amount": 1423448203.0}, {"time": "2026-06-18 13:29:00", "open": 44.45, "high": 44.45, "low": 44.45, "close": 44.45, "volume": 32590537.0, "amount": 1425055531.0}, {"time": "2026-06-18 13:30:00", "open": 44.44, "high": 44.44, "low": 44.44, "close": 44.44, "volume": 32624309.0, "amount": 1426556801.0}, {"time": "2026-06-18 13:31:00", "open": 44.54, "high": 44.54, "low": 44.54, "close": 44.54, "volume": 32719652.0, "amount": 1430797785.0}, {"time": "2026-06-18 13:32:00", "open": 44.53, "high": 44.53, "low": 44.53, "close": 44.53, "volume": 32742913.0, "amount": 1431833944.0}, {"time": "2026-06-18 13:33:00", "open": 44.41, "high": 44.41, "low": 44.41, "close": 44.41, "volume": 32783878.0, "amount": 1433655391.0}, {"time": "2026-06-18 13:34:00", "open": 44.49, "high": 44.49, "low": 44.49, "close": 44.49, "volume": 32808742.0, "amount": 1434760353.0}, {"time": "2026-06-18 13:35:00", "open": 44.45, "high": 44.45, "low": 44.45, "close": 44.45, "volume": 32873517.0, "amount": 1437641630.0}, {"time": "2026-06-18 13:36:00", "open": 44.42, "high": 44.42, "low": 44.42, "close": 44.42, "volume": 32906407.0, "amount": 1439103262.0}, {"time": "2026-06-18 13:37:00", "open": 44.3, "high": 44.3, "low": 44.3, "close": 44.3, "volume": 32947946.0, "amount": 1440946210.0}, {"time": "2026-06-18 13:38:00", "open": 44.27, "high": 44.27, "low": 44.27, "close": 44.27, "volume": 33023213.0, "amount": 1444279639.0}, {"time": "2026-06-18 13:39:00", "open": 44.2, "high": 44.2, "low": 44.2, "close": 44.2, "volume": 33069417.0, "amount": 1446322797.0}, {"time": "2026-06-18 13:40:00", "open": 44.21, "high": 44.21, "low": 44.21, "close": 44.21, "volume": 33104051.0, "amount": 1447853149.0}, {"time": "2026-06-18 13:41:00", "open": 44.17, "high": 44.17, "low": 44.17, "close": 44.17, "volume": 33154927.0, "amount": 1450102179.0}, {"time": "2026-06-18 13:42:00", "open": 44.19, "high": 44.19, "low": 44.19, "close": 44.19, "volume": 33207708.0, "amount": 1452434279.0}, {"time": "2026-06-18 13:43:00", "open": 44.41, "high": 44.41, "low": 44.41, "close": 44.41, "volume": 33268969.0, "amount": 1455146381.0}, {"time": "2026-06-18 13:44:00", "open": 44.4, "high": 44.4, "low": 44.4, "close": 44.4, "volume": 33305920.0, "amount": 1456788076.0}, {"time": "2026-06-18 13:45:00", "open": 44.27, "high": 44.27, "low": 44.27, "close": 44.27, "volume": 33339709.0, "amount": 1458286330.0}, {"time": "2026-06-18 13:46:00", "open": 44.21, "high": 44.21, "low": 44.21, "close": 44.21, "volume": 33372991.0, "amount": 1459757851.0}, {"time": "2026-06-18 13:47:00", "open": 44.26, "high": 44.26, "low": 44.26, "close": 44.26, "volume": 33426281.0, "amount": 1462114190.0}, {"time": "2026-06-18 13:48:00", "open": 44.24, "high": 44.24, "low": 44.24, "close": 44.24, "volume": 33468801.0, "amount": 1463995021.0}, {"time": "2026-06-18 13:49:00", "open": 44.29, "high": 44.29, "low": 44.29, "close": 44.29, "volume": 33593658.0, "amount": 1469515509.0}, {"time": "2026-06-18 13:50:00", "open": 44.2, "high": 44.2, "low": 44.2, "close": 44.2, "volume": 33612959.0, "amount": 1470369203.0}, {"time": "2026-06-18 13:51:00", "open": 44.2, "high": 44.2, "low": 44.2, "close": 44.2, "volume": 33667287.0, "amount": 1472770302.0}, {"time": "2026-06-18 13:52:00", "open": 44.22, "high": 44.22, "low": 44.22, "close": 44.22, "volume": 33717751.0, "amount": 1475000661.0}, {"time": "2026-06-18 13:53:00", "open": 44.4, "high": 44.4, "low": 44.4, "close": 44.4, "volume": 33790181.0, "amount": 1478209862.0}, {"time": "2026-06-18 13:54:00", "open": 44.43, "high": 44.43, "low": 44.43, "close": 44.43, "volume": 33829413.0, "amount": 1479952521.0}, {"time": "2026-06-18 13:55:00", "open": 44.39, "high": 44.39, "low": 44.39, "close": 44.39, "volume": 33844612.0, "amount": 1480627382.0}, {"time": "2026-06-18 13:56:00", "open": 44.4, "high": 44.4, "low": 44.4, "close": 44.4, "volume": 33886646.0, "amount": 1482493357.0}, {"time": "2026-06-18 13:57:00", "open": 44.4, "high": 44.4, "low": 44.4, "close": 44.4, "volume": 33919366.0, "amount": 1483945962.0}, {"time": "2026-06-18 13:58:00", "open": 44.4, "high": 44.4, "low": 44.4, "close": 44.4, "volume": 34055438.0, "amount": 1489990135.0}, {"time": "2026-06-18 13:59:00", "open": 44.5, "high": 44.5, "low": 44.5, "close": 44.5, "volume": 34122881.0, "amount": 1492991235.0}, {"time": "2026-06-18 14:00:00", "open": 44.45, "high": 44.45, "low": 44.45, "close": 44.45, "volume": 34193076.0, "amount": 1496115678.0}, {"time": "2026-06-18 14:01:00", "open": 44.45, "high": 44.45, "low": 44.45, "close": 44.45, "volume": 34213975.0, "amount": 1497044294.0}, {"time": "2026-06-18 14:02:00", "open": 44.5, "high": 44.5, "low": 44.5, "close": 44.5, "volume": 34271528.0, "amount": 1499605184.0}, {"time": "2026-06-18 14:03:00", "open": 44.49, "high": 44.49, "low": 44.49, "close": 44.49, "volume": 34318341.0, "amount": 1501687367.0}, {"time": "2026-06-18 14:04:00", "open": 44.46, "high": 44.46, "low": 44.46, "close": 44.46, "volume": 34342242.0, "amount": 1502749807.0}, {"time": "2026-06-18 14:05:00", "open": 44.44, "high": 44.44, "low": 44.44, "close": 44.44, "volume": 34384107.0, "amount": 1504610470.0}, {"time": "2026-06-18 14:06:00", "open": 44.44, "high": 44.44, "low": 44.44, "close": 44.44, "volume": 34436988.0, "amount": 1506959839.0}, {"time": "2026-06-18 14:07:00", "open": 44.51, "high": 44.51, "low": 44.51, "close": 44.51, "volume": 34598204.0, "amount": 1514133905.0}, {"time": "2026-06-18 14:08:00", "open": 44.48, "high": 44.48, "low": 44.48, "close": 44.48, "volume": 34664224.0, "amount": 1517070345.0}, {"time": "2026-06-18 14:09:00", "open": 44.5, "high": 44.5, "low": 44.5, "close": 44.5, "volume": 34731761.0, "amount": 1520074890.0}, {"time": "2026-06-18 14:10:00", "open": 44.47, "high": 44.47, "low": 44.47, "close": 44.47, "volume": 34774285.0, "amount": 1521966208.0}, {"time": "2026-06-18 14:11:00", "open": 44.46, "high": 44.46, "low": 44.46, "close": 44.46, "volume": 34793987.0, "amount": 1522842119.0}, {"time": "2026-06-18 14:12:00", "open": 44.44, "high": 44.44, "low": 44.44, "close": 44.44, "volume": 34838217.0, "amount": 1524808221.0}, {"time": "2026-06-18 14:13:00", "open": 44.63, "high": 44.63, "low": 44.63, "close": 44.63, "volume": 35040154.0, "amount": 1533801166.0}, {"time": "2026-06-18 14:14:00", "open": 44.65, "high": 44.65, "low": 44.65, "close": 44.65, "volume": 35089801.0, "amount": 1536017797.0}, {"time": "2026-06-18 14:15:00", "open": 44.59, "high": 44.59, "low": 44.59, "close": 44.59, "volume": 35126972.0, "amount": 1537675801.0}, {"time": "2026-06-18 14:16:00", "open": 44.54, "high": 44.54, "low": 44.54, "close": 44.54, "volume": 35187849.0, "amount": 1540388469.0}, {"time": "2026-06-18 14:17:00", "open": 44.52, "high": 44.52, "low": 44.52, "close": 44.52, "volume": 35217049.0, "amount": 1541688911.0}, {"time": "2026-06-18 14:18:00", "open": 44.52, "high": 44.52, "low": 44.52, "close": 44.52, "volume": 35282674.0, "amount": 1544610725.0}, {"time": "2026-06-18 14:19:00", "open": 44.48, "high": 44.48, "low": 44.48, "close": 44.48, "volume": 35361320.0, "amount": 1548110423.0}, {"time": "2026-06-18 14:20:00", "open": 44.48, "high": 44.48, "low": 44.48, "close": 44.48, "volume": 35394635.0, "amount": 1549592880.0}, {"time": "2026-06-18 14:21:00", "open": 44.48, "high": 44.48, "low": 44.48, "close": 44.48, "volume": 35420337.0, "amount": 1550736517.0}, {"time": "2026-06-18 14:22:00", "open": 44.47, "high": 44.47, "low": 44.47, "close": 44.47, "volume": 35453014.0, "amount": 1552189929.0}, {"time": "2026-06-18 14:23:00", "open": 44.2, "high": 44.2, "low": 44.2, "close": 44.2, "volume": 35586857.0, "amount": 1558132510.0}, {"time": "2026-06-18 14:24:00", "open": 44.4, "high": 44.4, "low": 44.4, "close": 44.4, "volume": 35701437.0, "amount": 1563217590.0}, {"time": "2026-06-18 14:25:00", "open": 44.45, "high": 44.45, "low": 44.45, "close": 44.45, "volume": 35736405.0, "amount": 1564771169.0}, {"time": "2026-06-18 14:26:00", "open": 44.4, "high": 44.4, "low": 44.4, "close": 44.4, "volume": 35785317.0, "amount": 1566943453.0}, {"time": "2026-06-18 14:27:00", "open": 44.34, "high": 44.34, "low": 44.34, "close": 44.34, "volume": 35818066.0, "amount": 1568396859.0}, {"time": "2026-06-18 14:28:00", "open": 44.47, "high": 44.47, "low": 44.47, "close": 44.47, "volume": 35952114.0, "amount": 1574347808.0}, {"time": "2026-06-18 14:29:00", "open": 44.66, "high": 44.66, "low": 44.66, "close": 44.66, "volume": 36280226.0, "amount": 1588963767.0}, {"time": "2026-06-18 14:30:00", "open": 44.77, "high": 44.77, "low": 44.77, "close": 44.77, "volume": 36422616.0, "amount": 1595329939.0}, {"time": "2026-06-18 14:31:00", "open": 44.82, "high": 44.82, "low": 44.82, "close": 44.82, "volume": 36601769.0, "amount": 1603359638.0}, {"time": "2026-06-18 14:32:00", "open": 45.13, "high": 45.13, "low": 45.13, "close": 45.13, "volume": 37197444.0, "amount": 1630133064.0}, {"time": "2026-06-18 14:33:00", "open": 45.35, "high": 45.35, "low": 45.35, "close": 45.35, "volume": 37813956.0, "amount": 1658057607.0}, {"time": "2026-06-18 14:34:00", "open": 45.01, "high": 45.01, "low": 45.01, "close": 45.01, "volume": 38108866.0, "amount": 1671384408.0}, {"time": "2026-06-18 14:35:00", "open": 44.89, "high": 44.89, "low": 44.89, "close": 44.89, "volume": 38454882.0, "amount": 1686936217.0}, {"time": "2026-06-18 14:36:00", "open": 45.05, "high": 45.05, "low": 45.05, "close": 45.05, "volume": 38652699.0, "amount": 1695827198.0}, {"time": "2026-06-18 14:37:00", "open": 44.85, "high": 44.85, "low": 44.85, "close": 44.85, "volume": 38819164.0, "amount": 1703317710.0}, {"time": "2026-06-18 14:38:00", "open": 45.15, "high": 45.15, "low": 45.15, "close": 45.15, "volume": 39235458.0, "amount": 1722064672.0}, {"time": "2026-06-18 14:39:00", "open": 45.15, "high": 45.15, "low": 45.15, "close": 45.15, "volume": 39593657.0, "amount": 1738242094.0}, {"time": "2026-06-18 14:40:00", "open": 44.85, "high": 44.85, "low": 44.85, "close": 44.85, "volume": 39673206.0, "amount": 1741816677.0}, {"time": "2026-06-18 14:41:00", "open": 44.9, "high": 44.9, "low": 44.9, "close": 44.9, "volume": 39861915.0, "amount": 1750281760.0}, {"time": "2026-06-18 14:42:00", "open": 44.96, "high": 44.96, "low": 44.96, "close": 44.96, "volume": 40000151.0, "amount": 1756491274.0}, {"time": "2026-06-18 14:43:00", "open": 45.09, "high": 45.09, "low": 45.09, "close": 45.09, "volume": 40219099.0, "amount": 1766339866.0}, {"time": "2026-06-18 14:44:00", "open": 45.13, "high": 45.13, "low": 45.13, "close": 45.13, "volume": 40400889.0, "amount": 1774537276.0}, {"time": "2026-06-18 14:45:00", "open": 45.64, "high": 45.64, "low": 45.64, "close": 45.64, "volume": 42377529.0, "amount": 1864376107.0}, {"time": "2026-06-18 14:46:00", "open": 45.56, "high": 45.56, "low": 45.56, "close": 45.56, "volume": 42866633.0, "amount": 1886664052.0}, {"time": "2026-06-18 14:47:00", "open": 45.7, "high": 45.7, "low": 45.7, "close": 45.7, "volume": 43544089.0, "amount": 1917567351.0}, {"time": "2026-06-18 14:48:00", "open": 45.97, "high": 45.97, "low": 45.97, "close": 45.97, "volume": 44669788.0, "amount": 1969291816.0}, {"time": "2026-06-18 14:49:00", "open": 45.97, "high": 45.97, "low": 45.97, "close": 45.97, "volume": 45031547.0, "amount": 1985908101.0}, {"time": "2026-06-18 14:50:00", "open": 46.08, "high": 46.08, "low": 46.08, "close": 46.08, "volume": 45847585.0, "amount": 2023489906.0}, {"time": "2026-06-18 14:51:00", "open": 45.97, "high": 45.97, "low": 45.97, "close": 45.97, "volume": 46111983.0, "amount": 2035653111.0}, {"time": "2026-06-18 14:52:00", "open": 45.89, "high": 45.89, "low": 45.89, "close": 45.89, "volume": 46444580.0, "amount": 2050937100.0}, {"time": "2026-06-18 14:53:00", "open": 45.7, "high": 45.7, "low": 45.7, "close": 45.7, "volume": 46640521.0, "amount": 2059896925.0}, {"time": "2026-06-18 14:54:00", "open": 45.8, "high": 45.8, "low": 45.8, "close": 45.8, "volume": 47039875.0, "amount": 2078142313.0}, {"time": "2026-06-18 14:55:00", "open": 45.88, "high": 45.88, "low": 45.88, "close": 45.88, "volume": 47329182.0, "amount": 2091405283.0}, {"time": "2026-06-18 14:56:00", "open": 45.78, "high": 45.78, "low": 45.78, "close": 45.78, "volume": 47552321.0, "amount": 2101627106.0}, {"time": "2026-06-18 14:57:00", "open": 45.74, "high": 45.74, "low": 45.74, "close": 45.74, "volume": 47904863.0, "amount": 2117763301.0}, {"time": "2026-06-18 14:58:00", "open": 45.74, "high": 45.74, "low": 45.74, "close": 45.74, "volume": 47908201.0, "amount": 2117916007.0}, {"time": "2026-06-18 14:59:00", "open": 45.74, "high": 45.74, "low": 45.74, "close": 45.74, "volume": 47908201.0, "amount": 2117916007.0}]}