{"code": "002015", "name": "协鑫能科", "date": "2026-07-13", "saved_at": "2026-07-13 15:00:04", "row_count": 241, "last_time": "2026-07-13 14:59:00", "last_close": 14.05, "last_vwap": 14.232036931108745, "market_state": "trend_down", "benchmark_code": "sz399001", "benchmark_name": "深证成指", "benchmark_state": "range_bound", "benchmark_gate": "neutral", "benchmark_reason": "指数中性", "signal": {"action": "SELL_HIGH", "score": 76, "reasons": ["长上影", "EMA转弱", "短期压力受阻(MA5)", "强空头优先高抛", "日线破位风险", "日线硬破位"], "entry_kind": "sell_high"}, "daily_context": {"daily_status": "ok", "daily_reason": "", "daily_asof": "2026-07-13", "daily_price_ref": 14.08, "daily_prev_close": 14.88, "daily_prev_low": 14.41, "daily_day_ret": -0.053763440860215096, "daily_prev_day_ret": 0.0362116991643455, "daily_ma5": 14.496, "daily_ma5_slope": -0.08772813089993707, "daily_above_ma5": false, "daily_ma5_gap": -0.028697571743929385, "daily_ma5_state": "below_ma5_weak", "daily_ma10": 15.193000000000001, "daily_ma20": 16.557, "daily_ma30": 18.027333333333335, "daily_ma60": 19.224333333333334, "daily_ma120": NaN, "daily_ma150": NaN, "daily_ma180": NaN, "daily_ma250": NaN, "daily_ma365": NaN, "daily_ma10_slope": -0.08514481845005106, "daily_ma20_slope": -0.059528543027548904, "daily_ma30_slope": -0.06729442604856502, "daily_ma60_slope": -0.012719118049849392, "daily_ma120_slope": NaN, "daily_ma150_slope": NaN, "daily_ma180_slope": NaN, "daily_ma250_slope": NaN, "daily_ma365_slope": NaN, "daily_trend_bg": "weak_breakdown", "daily_gate": "risk", "daily_support_name": "MA5", "daily_support_level": 14.496, "daily_support_gap": 0.028697571743929385, "daily_near_support": true, "daily_pullback_support": false, "daily_breakdown_risk": true, "daily_hard_breakdown": true, "daily_overheated": false, "daily_ma_clustered": false, "daily_bull_aligned": false}, "bars": [{"time": "2026-07-13 09:30:00", "open": 14.83, "high": 14.83, "low": 14.83, "close": 14.83, "volume": 2976.0, "amount": 4413408.0}, {"time": "2026-07-13 09:31:00", "open": 14.75, "high": 14.75, "low": 14.75, "close": 14.75, "volume": 17919.0, "amount": 26533329.3}, {"time": "2026-07-13 09:32:00", "open": 14.75, "high": 14.75, "low": 14.75, "close": 14.75, "volume": 29536.0, "amount": 43672780.76}, {"time": "2026-07-13 09:33:00", "open": 14.91, "high": 14.91, "low": 14.91, "close": 14.91, "volume": 36656.0, "amount": 54241841.76}, {"time": "2026-07-13 09:34:00", "open": 14.84, "high": 14.84, "low": 14.84, "close": 14.84, "volume": 41955.0, "amount": 62109935.76}, {"time": "2026-07-13 09:35:00", "open": 14.85, "high": 14.85, "low": 14.85, "close": 14.85, "volume": 49715.0, "amount": 73607457.76}, {"time": "2026-07-13 09:36:00", "open": 14.72, "high": 14.72, "low": 14.72, "close": 14.72, "volume": 58016.0, "amount": 85878856.76}, {"time": "2026-07-13 09:37:00", "open": 14.8, "high": 14.8, "low": 14.8, "close": 14.8, "volume": 64352.0, "amount": 95223473.14}, {"time": "2026-07-13 09:38:00", "open": 14.81, "high": 14.81, "low": 14.81, "close": 14.81, "volume": 67979.0, "amount": 100588760.13}, {"time": "2026-07-13 09:39:00", "open": 14.89, "high": 14.89, "low": 14.89, "close": 14.89, "volume": 74144.0, "amount": 109729843.24}, {"time": "2026-07-13 09:40:00", "open": 14.87, "high": 14.87, "low": 14.87, "close": 14.87, "volume": 79201.0, "amount": 117253795.47}, {"time": "2026-07-13 09:41:00", "open": 14.86, "high": 14.86, "low": 14.86, "close": 14.86, "volume": 85416.0, "amount": 126460870.95}, {"time": "2026-07-13 09:42:00", "open": 14.9, "high": 14.9, "low": 14.9, "close": 14.9, "volume": 90344.0, "amount": 133792406.74}, {"time": "2026-07-13 09:43:00", "open": 14.93, "high": 14.93, "low": 14.93, "close": 14.93, "volume": 103263.0, "amount": 153060961.18}, {"time": "2026-07-13 09:44:00", "open": 14.78, "high": 14.78, "low": 14.78, "close": 14.78, "volume": 111200.0, "amount": 164832616.2}, {"time": "2026-07-13 09:45:00", "open": 14.8, "high": 14.8, "low": 14.8, "close": 14.8, "volume": 115673.0, "amount": 171443246.14}, {"time": "2026-07-13 09:46:00", "open": 14.79, "high": 14.79, "low": 14.79, "close": 14.79, "volume": 120227.0, "amount": 178184255.11}, {"time": "2026-07-13 09:47:00", "open": 14.69, "high": 14.69, "low": 14.69, "close": 14.69, "volume": 129630.0, "amount": 192042308.89}, {"time": "2026-07-13 09:48:00", "open": 14.69, "high": 14.69, "low": 14.69, "close": 14.69, "volume": 137382.0, "amount": 203426096.62}, {"time": "2026-07-13 09:49:00", "open": 14.65, "high": 14.65, "low": 14.65, "close": 14.65, "volume": 143359.0, "amount": 212185823.39}, {"time": "2026-07-13 09:50:00", "open": 14.62, "high": 14.62, "low": 14.62, "close": 14.62, "volume": 147721.0, "amount": 218571764.21}, {"time": "2026-07-13 09:51:00", "open": 14.63, "high": 14.63, "low": 14.63, "close": 14.63, "volume": 154030.0, "amount": 227797874.95}, {"time": "2026-07-13 09:52:00", "open": 14.67, "high": 14.67, "low": 14.67, "close": 14.67, "volume": 156960.0, "amount": 232092921.86}, {"time": "2026-07-13 09:53:00", "open": 14.65, "high": 14.65, "low": 14.65, "close": 14.65, "volume": 159788.0, "amount": 236233578.38}, {"time": "2026-07-13 09:54:00", "open": 14.61, "high": 14.61, "low": 14.61, "close": 14.61, "volume": 164934.0, "amount": 243753393.42}, {"time": "2026-07-13 09:55:00", "open": 14.56, "high": 14.56, "low": 14.56, "close": 14.56, "volume": 172403.0, "amount": 254637216.49}, {"time": "2026-07-13 09:56:00", "open": 14.51, "high": 14.51, "low": 14.51, "close": 14.51, "volume": 177566.0, "amount": 262142465.55}, {"time": "2026-07-13 09:57:00", "open": 14.53, "high": 14.53, "low": 14.53, "close": 14.53, "volume": 180900.0, "amount": 266983258.58}, {"time": "2026-07-13 09:58:00", "open": 14.48, "high": 14.48, "low": 14.48, "close": 14.48, "volume": 187773.0, "amount": 276949456.66}, {"time": "2026-07-13 09:59:00", "open": 14.46, "high": 14.46, "low": 14.46, "close": 14.46, "volume": 192682.0, "amount": 284052651.71}, {"time": "2026-07-13 10:00:00", "open": 14.48, "high": 14.48, "low": 14.48, "close": 14.48, "volume": 197958.0, "amount": 291681290.77}, {"time": "2026-07-13 10:01:00", "open": 14.46, "high": 14.46, "low": 14.46, "close": 14.46, "volume": 201791.0, "amount": 297228590.81}, {"time": "2026-07-13 10:02:00", "open": 14.46, "high": 14.46, "low": 14.46, "close": 14.46, "volume": 204923.0, "amount": 301759064.85}, {"time": "2026-07-13 10:03:00", "open": 14.45, "high": 14.45, "low": 14.45, "close": 14.45, "volume": 209424.0, "amount": 308264474.89}, {"time": "2026-07-13 10:04:00", "open": 14.37, "high": 14.37, "low": 14.37, "close": 14.37, "volume": 215631.0, "amount": 317206977.96}, {"time": "2026-07-13 10:05:00", "open": 14.48, "high": 14.48, "low": 14.48, "close": 14.48, "volume": 220211.0, "amount": 323810414.01}, {"time": "2026-07-13 10:06:00", "open": 14.48, "high": 14.48, "low": 14.48, "close": 14.48, "volume": 222761.0, "amount": 327502195.03}, {"time": "2026-07-13 10:07:00", "open": 14.49, "high": 14.49, "low": 14.49, "close": 14.49, "volume": 224434.0, "amount": 329923956.05}, {"time": "2026-07-13 10:08:00", "open": 14.45, "high": 14.45, "low": 14.45, "close": 14.45, "volume": 226183.0, "amount": 332455092.06}, {"time": "2026-07-13 10:09:00", "open": 14.44, "high": 14.44, "low": 14.44, "close": 14.44, "volume": 227475.0, "amount": 334321513.07}, {"time": "2026-07-13 10:10:00", "open": 14.46, "high": 14.46, "low": 14.46, "close": 14.46, "volume": 228516.0, "amount": 335826228.08}, {"time": "2026-07-13 10:11:00", "open": 14.44, "high": 14.44, "low": 14.44, "close": 14.44, "volume": 229878.0, "amount": 337792737.09}, {"time": "2026-07-13 10:12:00", "open": 14.46, "high": 14.46, "low": 14.46, "close": 14.46, "volume": 231498.0, "amount": 340132761.11}, {"time": "2026-07-13 10:13:00", "open": 14.47, "high": 14.47, "low": 14.47, "close": 14.47, "volume": 233204.0, "amount": 342602524.12}, {"time": "2026-07-13 10:14:00", "open": 14.59, "high": 14.59, "low": 14.59, "close": 14.59, "volume": 236068.0, "amount": 346763730.14}, {"time": "2026-07-13 10:15:00", "open": 14.59, "high": 14.59, "low": 14.59, "close": 14.59, "volume": 237718.0, "amount": 349167797.14}, {"time": "2026-07-13 10:16:00", "open": 14.55, "high": 14.55, "low": 14.55, "close": 14.55, "volume": 239241.0, "amount": 351386784.15}, {"time": "2026-07-13 10:17:00", "open": 14.55, "high": 14.55, "low": 14.55, "close": 14.55, "volume": 240822.0, "amount": 353686546.16}, {"time": "2026-07-13 10:18:00", "open": 14.51, "high": 14.51, "low": 14.51, "close": 14.51, "volume": 241868.0, "amount": 355205964.16}, {"time": "2026-07-13 10:19:00", "open": 14.5, "high": 14.5, "low": 14.5, "close": 14.5, "volume": 242502.0, "amount": 356126021.17}, {"time": "2026-07-13 10:20:00", "open": 14.5, "high": 14.5, "low": 14.5, "close": 14.5, "volume": 243287.0, "amount": 357264136.17}, {"time": "2026-07-13 10:21:00", "open": 14.49, "high": 14.49, "low": 14.49, "close": 14.49, "volume": 244745.0, "amount": 359376257.18}, {"time": "2026-07-13 10:22:00", "open": 14.48, "high": 14.48, "low": 14.48, "close": 14.48, "volume": 245349.0, "amount": 360250621.18}, {"time": "2026-07-13 10:23:00", "open": 14.48, "high": 14.48, "low": 14.48, "close": 14.48, "volume": 246283.0, "amount": 361602565.19}, {"time": "2026-07-13 10:24:00", "open": 14.46, "high": 14.46, "low": 14.46, "close": 14.46, "volume": 247388.0, "amount": 363201509.2}, {"time": "2026-07-13 10:25:00", "open": 14.52, "high": 14.52, "low": 14.52, "close": 14.52, "volume": 249212.0, "amount": 365846088.21}, {"time": "2026-07-13 10:26:00", "open": 14.53, "high": 14.53, "low": 14.53, "close": 14.53, "volume": 250013.0, "amount": 367010540.21}, {"time": "2026-07-13 10:27:00", "open": 14.52, "high": 14.52, "low": 14.52, "close": 14.52, "volume": 250706.0, "amount": 368016976.22}, {"time": "2026-07-13 10:28:00", "open": 14.53, "high": 14.53, "low": 14.53, "close": 14.53, "volume": 251305.0, "amount": 368886915.22}, {"time": "2026-07-13 10:29:00", "open": 14.5, "high": 14.5, "low": 14.5, "close": 14.5, "volume": 252261.0, "amount": 370274433.22}, {"time": "2026-07-13 10:30:00", "open": 14.49, "high": 14.49, "low": 14.49, "close": 14.49, "volume": 253701.0, "amount": 372362360.23}, {"time": "2026-07-13 10:31:00", "open": 14.47, "high": 14.47, "low": 14.47, "close": 14.47, "volume": 254597.0, "amount": 373660185.24}, {"time": "2026-07-13 10:32:00", "open": 14.46, "high": 14.46, "low": 14.46, "close": 14.46, "volume": 256221.0, "amount": 376009639.25}, {"time": "2026-07-13 10:33:00", "open": 14.44, "high": 14.44, "low": 14.44, "close": 14.44, "volume": 257214.0, "amount": 377444409.26}, {"time": "2026-07-13 10:34:00", "open": 14.45, "high": 14.45, "low": 14.45, "close": 14.45, "volume": 257991.0, "amount": 378567123.26}, {"time": "2026-07-13 10:35:00", "open": 14.44, "high": 14.44, "low": 14.44, "close": 14.44, "volume": 259655.0, "amount": 380971043.27}, {"time": "2026-07-13 10:36:00", "open": 14.44, "high": 14.44, "low": 14.44, "close": 14.44, "volume": 261171.0, "amount": 383159698.28}, {"time": "2026-07-13 10:37:00", "open": 14.38, "high": 14.38, "low": 14.38, "close": 14.38, "volume": 264641.0, "amount": 388159418.31}, {"time": "2026-07-13 10:38:00", "open": 14.32, "high": 14.32, "low": 14.32, "close": 14.32, "volume": 267975.0, "amount": 392944626.34}, {"time": "2026-07-13 10:39:00", "open": 14.33, "high": 14.33, "low": 14.33, "close": 14.33, "volume": 270073.0, "amount": 395947857.36}, {"time": "2026-07-13 10:40:00", "open": 14.31, "high": 14.31, "low": 14.31, "close": 14.31, "volume": 272317.0, "amount": 399159882.39}, {"time": "2026-07-13 10:41:00", "open": 14.31, "high": 14.31, "low": 14.31, "close": 14.31, "volume": 273902.0, "amount": 401427615.4}, {"time": "2026-07-13 10:42:00", "open": 14.31, "high": 14.31, "low": 14.31, "close": 14.31, "volume": 275256.0, "amount": 403364246.42}, {"time": "2026-07-13 10:43:00", "open": 14.32, "high": 14.32, "low": 14.32, "close": 14.32, "volume": 276622.0, "amount": 405318408.43}, {"time": "2026-07-13 10:44:00", "open": 14.31, "high": 14.31, "low": 14.31, "close": 14.31, "volume": 277754.0, "amount": 406938345.44}, {"time": "2026-07-13 10:45:00", "open": 14.32, "high": 14.32, "low": 14.32, "close": 14.32, "volume": 279227.0, "amount": 409045948.46}, {"time": "2026-07-13 10:46:00", "open": 14.32, "high": 14.32, "low": 14.32, "close": 14.32, "volume": 282914.0, "amount": 414320860.49}, {"time": "2026-07-13 10:47:00", "open": 14.35, "high": 14.35, "low": 14.35, "close": 14.35, "volume": 283619.0, "amount": 415331763.5}, {"time": "2026-07-13 10:48:00", "open": 14.35, "high": 14.35, "low": 14.35, "close": 14.35, "volume": 285281.0, "amount": 417716472.51}, {"time": "2026-07-13 10:49:00", "open": 14.34, "high": 14.34, "low": 14.34, "close": 14.34, "volume": 286724.0, "amount": 419785491.52}, {"time": "2026-07-13 10:50:00", "open": 14.36, "high": 14.36, "low": 14.36, "close": 14.36, "volume": 287542.0, "amount": 420959183.53}, {"time": "2026-07-13 10:51:00", "open": 14.36, "high": 14.36, "low": 14.36, "close": 14.36, "volume": 288370.0, "amount": 422147649.54}, {"time": "2026-07-13 10:52:00", "open": 14.36, "high": 14.36, "low": 14.36, "close": 14.36, "volume": 289265.0, "amount": 423432558.54}, {"time": "2026-07-13 10:53:00", "open": 14.36, "high": 14.36, "low": 14.36, "close": 14.36, "volume": 290071.0, "amount": 424589625.55}, {"time": "2026-07-13 10:54:00", "open": 14.36, "high": 14.36, "low": 14.36, "close": 14.36, "volume": 290758.0, "amount": 425576099.56}, {"time": "2026-07-13 10:55:00", "open": 14.33, "high": 14.33, "low": 14.33, "close": 14.33, "volume": 292236.0, "amount": 427696774.57}, {"time": "2026-07-13 10:56:00", "open": 14.32, "high": 14.32, "low": 14.32, "close": 14.32, "volume": 293356.0, "amount": 429301474.58}, {"time": "2026-07-13 10:57:00", "open": 14.31, "high": 14.31, "low": 14.31, "close": 14.31, "volume": 293868.0, "amount": 430034279.58}, {"time": "2026-07-13 10:58:00", "open": 14.31, "high": 14.31, "low": 14.31, "close": 14.31, "volume": 294656.0, "amount": 431162296.59}, {"time": "2026-07-13 10:59:00", "open": 14.31, "high": 14.31, "low": 14.31, "close": 14.31, "volume": 295424.0, "amount": 432260772.59}, {"time": "2026-07-13 11:00:00", "open": 14.33, "high": 14.33, "low": 14.33, "close": 14.33, "volume": 296429.0, "amount": 433700096.6}, {"time": "2026-07-13 11:01:00", "open": 14.31, "high": 14.31, "low": 14.31, "close": 14.31, "volume": 297092.0, "amount": 434649353.61}, {"time": "2026-07-13 11:02:00", "open": 14.36, "high": 14.36, "low": 14.36, "close": 14.36, "volume": 298050.0, "amount": 436022954.62}, {"time": "2026-07-13 11:03:00", "open": 14.32, "high": 14.32, "low": 14.32, "close": 14.32, "volume": 299564.0, "amount": 438193742.63}, {"time": "2026-07-13 11:04:00", "open": 14.34, "high": 14.34, "low": 14.34, "close": 14.34, "volume": 300691.0, "amount": 439810110.64}, {"time": "2026-07-13 11:05:00", "open": 14.32, "high": 14.32, "low": 14.32, "close": 14.32, "volume": 301419.0, "amount": 440852895.64}, {"time": "2026-07-13 11:06:00", "open": 14.31, "high": 14.31, "low": 14.31, "close": 14.31, "volume": 302787.0, "amount": 442811224.65}, {"time": "2026-07-13 11:07:00", "open": 14.27, "high": 14.27, "low": 14.27, "close": 14.27, "volume": 306013.0, "amount": 447420093.68}, {"time": "2026-07-13 11:08:00", "open": 14.29, "high": 14.29, "low": 14.29, "close": 14.29, "volume": 307098.0, "amount": 448969513.69}, {"time": "2026-07-13 11:09:00", "open": 14.28, "high": 14.28, "low": 14.28, "close": 14.28, "volume": 309959.0, "amount": 453051118.72}, {"time": "2026-07-13 11:10:00", "open": 14.27, "high": 14.27, "low": 14.27, "close": 14.27, "volume": 311205.0, "amount": 454829264.73}, {"time": "2026-07-13 11:11:00", "open": 14.27, "high": 14.27, "low": 14.27, "close": 14.27, "volume": 312528.0, "amount": 456717710.74}, {"time": "2026-07-13 11:12:00", "open": 14.27, "high": 14.27, "low": 14.27, "close": 14.27, "volume": 313538.0, "amount": 458159550.75}, {"time": "2026-07-13 11:13:00", "open": 14.28, "high": 14.28, "low": 14.28, "close": 14.28, "volume": 315032.0, "amount": 460293259.76}, {"time": "2026-07-13 11:14:00", "open": 14.27, "high": 14.27, "low": 14.27, "close": 14.27, "volume": 316436.0, "amount": 462298085.77}, {"time": "2026-07-13 11:15:00", "open": 14.28, "high": 14.28, "low": 14.28, "close": 14.28, "volume": 317911.0, "amount": 464402845.79}, {"time": "2026-07-13 11:16:00", "open": 14.32, "high": 14.32, "low": 14.32, "close": 14.32, "volume": 319022.0, "amount": 465992108.79}, {"time": "2026-07-13 11:17:00", "open": 14.32, "high": 14.32, "low": 14.32, "close": 14.32, "volume": 320317.0, "amount": 467846229.8}, {"time": "2026-07-13 11:18:00", "open": 14.3, "high": 14.3, "low": 14.3, "close": 14.3, "volume": 321775.0, "amount": 469932568.81}, {"time": "2026-07-13 11:19:00", "open": 14.35, "high": 14.35, "low": 14.35, "close": 14.35, "volume": 322814.0, "amount": 471420934.82}, {"time": "2026-07-13 11:20:00", "open": 14.31, "high": 14.31, "low": 14.31, "close": 14.31, "volume": 323851.0, "amount": 472908276.83}, {"time": "2026-07-13 11:21:00", "open": 14.29, "high": 14.29, "low": 14.29, "close": 14.29, "volume": 325001.0, "amount": 474552305.84}, {"time": "2026-07-13 11:22:00", "open": 14.3, "high": 14.3, "low": 14.3, "close": 14.3, "volume": 325780.0, "amount": 475666240.84}, {"time": "2026-07-13 11:23:00", "open": 14.31, "high": 14.31, "low": 14.31, "close": 14.31, "volume": 326250.0, "amount": 476339004.85}, {"time": "2026-07-13 11:24:00", "open": 14.27, "high": 14.27, "low": 14.27, "close": 14.27, "volume": 327859.0, "amount": 478636300.86}, {"time": "2026-07-13 11:25:00", "open": 14.29, "high": 14.29, "low": 14.29, "close": 14.29, "volume": 329517.0, "amount": 481002500.87}, {"time": "2026-07-13 11:26:00", "open": 14.29, "high": 14.29, "low": 14.29, "close": 14.29, "volume": 330222.0, "amount": 482010303.88}, {"time": "2026-07-13 11:27:00", "open": 14.27, "high": 14.27, "low": 14.27, "close": 14.27, "volume": 330938.0, "amount": 483032725.88}, {"time": "2026-07-13 11:28:00", "open": 14.29, "high": 14.29, "low": 14.29, "close": 14.29, "volume": 332974.0, "amount": 485940107.9}, {"time": "2026-07-13 11:29:00", "open": 14.28, "high": 14.28, "low": 14.28, "close": 14.28, "volume": 333781.0, "amount": 487092993.9}, {"time": "2026-07-13 11:30:00", "open": 14.29, "high": 14.29, "low": 14.29, "close": 14.29, "volume": 334397.0, "amount": 487972869.91}, {"time": "2026-07-13 13:00:00", "open": 14.29, "high": 14.29, "low": 14.29, "close": 14.29, "volume": 334397.0, "amount": 487972869.91}, {"time": "2026-07-13 13:01:00", "open": 14.23, "high": 14.23, "low": 14.23, "close": 14.23, "volume": 339017.0, "amount": 494561429.95}, {"time": "2026-07-13 13:02:00", "open": 14.23, "high": 14.23, "low": 14.23, "close": 14.23, "volume": 340718.0, "amount": 496982857.96}, {"time": "2026-07-13 13:03:00", "open": 14.19, "high": 14.19, "low": 14.19, "close": 14.19, "volume": 344621.0, "amount": 502527503.99}, {"time": "2026-07-13 13:04:00", "open": 14.25, "high": 14.25, "low": 14.25, "close": 14.25, "volume": 348284.0, "amount": 507732908.02}, {"time": "2026-07-13 13:05:00", "open": 14.23, "high": 14.23, "low": 14.23, "close": 14.23, "volume": 349718.0, "amount": 509775809.04}, {"time": "2026-07-13 13:06:00", "open": 14.23, "high": 14.23, "low": 14.23, "close": 14.23, "volume": 352065.0, "amount": 513113073.05}, {"time": "2026-07-13 13:07:00", "open": 14.25, "high": 14.25, "low": 14.25, "close": 14.25, "volume": 352678.0, "amount": 513985486.06}, {"time": "2026-07-13 13:08:00", "open": 14.23, "high": 14.23, "low": 14.23, "close": 14.23, "volume": 353483.0, "amount": 515130907.07}, {"time": "2026-07-13 13:09:00", "open": 14.21, "high": 14.21, "low": 14.21, "close": 14.21, "volume": 354507.0, "amount": 516586665.07}, {"time": "2026-07-13 13:10:00", "open": 14.22, "high": 14.22, "low": 14.22, "close": 14.22, "volume": 355238.0, "amount": 517625564.08}, {"time": "2026-07-13 13:11:00", "open": 14.21, "high": 14.21, "low": 14.21, "close": 14.21, "volume": 356022.0, "amount": 518740451.09}, {"time": "2026-07-13 13:12:00", "open": 14.25, "high": 14.25, "low": 14.25, "close": 14.25, "volume": 356858.0, "amount": 519930084.09}, {"time": "2026-07-13 13:13:00", "open": 14.23, "high": 14.23, "low": 14.23, "close": 14.23, "volume": 357996.0, "amount": 521550352.1}, {"time": "2026-07-13 13:14:00", "open": 14.23, "high": 14.23, "low": 14.23, "close": 14.23, "volume": 358904.0, "amount": 522842456.11}, {"time": "2026-07-13 13:15:00", "open": 14.23, "high": 14.23, "low": 14.23, "close": 14.23, "volume": 359665.0, "amount": 523924845.11}, {"time": "2026-07-13 13:16:00", "open": 14.21, "high": 14.21, "low": 14.21, "close": 14.21, "volume": 361303.0, "amount": 526253197.13}, {"time": "2026-07-13 13:17:00", "open": 14.18, "high": 14.18, "low": 14.18, "close": 14.18, "volume": 363461.0, "amount": 529316677.14}, {"time": "2026-07-13 13:18:00", "open": 14.15, "high": 14.15, "low": 14.15, "close": 14.15, "volume": 366504.0, "amount": 533628353.17}, {"time": "2026-07-13 13:19:00", "open": 14.15, "high": 14.15, "low": 14.15, "close": 14.15, "volume": 368548.0, "amount": 536521264.19}, {"time": "2026-07-13 13:20:00", "open": 14.18, "high": 14.18, "low": 14.18, "close": 14.18, "volume": 369936.0, "amount": 538488226.2}, {"time": "2026-07-13 13:21:00", "open": 14.17, "high": 14.17, "low": 14.17, "close": 14.17, "volume": 370730.0, "amount": 539614012.21}, {"time": "2026-07-13 13:22:00", "open": 14.18, "high": 14.18, "low": 14.18, "close": 14.18, "volume": 371794.0, "amount": 541122399.22}, {"time": "2026-07-13 13:23:00", "open": 14.19, "high": 14.19, "low": 14.19, "close": 14.19, "volume": 372696.0, "amount": 542401991.22}, {"time": "2026-07-13 13:24:00", "open": 14.18, "high": 14.18, "low": 14.18, "close": 14.18, "volume": 373830.0, "amount": 544010038.23}, {"time": "2026-07-13 13:25:00", "open": 14.19, "high": 14.19, "low": 14.19, "close": 14.19, "volume": 375721.0, "amount": 546689276.25}, {"time": "2026-07-13 13:26:00", "open": 14.17, "high": 14.17, "low": 14.17, "close": 14.17, "volume": 376695.0, "amount": 548070102.25}, {"time": "2026-07-13 13:27:00", "open": 14.17, "high": 14.17, "low": 14.17, "close": 14.17, "volume": 377839.0, "amount": 549690314.26}, {"time": "2026-07-13 13:28:00", "open": 14.16, "high": 14.16, "low": 14.16, "close": 14.16, "volume": 378660.0, "amount": 550852700.27}, {"time": "2026-07-13 13:29:00", "open": 14.11, "high": 14.11, "low": 14.11, "close": 14.11, "volume": 382168.0, "amount": 555809485.3}, {"time": "2026-07-13 13:30:00", "open": 14.16, "high": 14.16, "low": 14.16, "close": 14.16, "volume": 384360.0, "amount": 558905613.32}, {"time": "2026-07-13 13:31:00", "open": 14.19, "high": 14.19, "low": 14.19, "close": 14.19, "volume": 385304.0, "amount": 560243784.33}, {"time": "2026-07-13 13:32:00", "open": 14.22, "high": 14.22, "low": 14.22, "close": 14.22, "volume": 386957.0, "amount": 562592527.34}, {"time": "2026-07-13 13:33:00", "open": 14.22, "high": 14.22, "low": 14.22, "close": 14.22, "volume": 388237.0, "amount": 564411332.35}, {"time": "2026-07-13 13:34:00", "open": 14.26, "high": 14.26, "low": 14.26, "close": 14.26, "volume": 389701.0, "amount": 566496120.36}, {"time": "2026-07-13 13:35:00", "open": 14.29, "high": 14.29, "low": 14.29, "close": 14.29, "volume": 391933.0, "amount": 569684800.37}, {"time": "2026-07-13 13:36:00", "open": 14.29, "high": 14.29, "low": 14.29, "close": 14.29, "volume": 395173.0, "amount": 574314348.38}, {"time": "2026-07-13 13:37:00", "open": 14.27, "high": 14.27, "low": 14.27, "close": 14.27, "volume": 396933.0, "amount": 576825791.39}, {"time": "2026-07-13 13:38:00", "open": 14.28, "high": 14.28, "low": 14.28, "close": 14.28, "volume": 397986.0, "amount": 578326370.4}, {"time": "2026-07-13 13:39:00", "open": 14.3, "high": 14.3, "low": 14.3, "close": 14.3, "volume": 399009.0, "amount": 579787595.4}, {"time": "2026-07-13 13:40:00", "open": 14.29, "high": 14.29, "low": 14.29, "close": 14.29, "volume": 400104.0, "amount": 581352942.41}, {"time": "2026-07-13 13:41:00", "open": 14.3, "high": 14.3, "low": 14.3, "close": 14.3, "volume": 401170.0, "amount": 582876095.41}, {"time": "2026-07-13 13:42:00", "open": 14.3, "high": 14.3, "low": 14.3, "close": 14.3, "volume": 402147.0, "amount": 584273368.42}, {"time": "2026-07-13 13:43:00", "open": 14.24, "high": 14.24, "low": 14.24, "close": 14.24, "volume": 403357.0, "amount": 585999469.43}, {"time": "2026-07-13 13:44:00", "open": 14.18, "high": 14.18, "low": 14.18, "close": 14.18, "volume": 405149.0, "amount": 588546627.44}, {"time": "2026-07-13 13:45:00", "open": 14.2, "high": 14.2, "low": 14.2, "close": 14.2, "volume": 406628.0, "amount": 590645037.45}, {"time": "2026-07-13 13:46:00", "open": 14.16, "high": 14.16, "low": 14.16, "close": 14.16, "volume": 407686.0, "amount": 592145039.45}, {"time": "2026-07-13 13:47:00", "open": 14.14, "high": 14.14, "low": 14.14, "close": 14.14, "volume": 408674.0, "amount": 593543326.46}, {"time": "2026-07-13 13:48:00", "open": 14.13, "high": 14.13, "low": 14.13, "close": 14.13, "volume": 409680.0, "amount": 594965297.47}, {"time": "2026-07-13 13:49:00", "open": 14.11, "high": 14.11, "low": 14.11, "close": 14.11, "volume": 411393.0, "amount": 597382882.48}, {"time": "2026-07-13 13:50:00", "open": 14.12, "high": 14.12, "low": 14.12, "close": 14.12, "volume": 412769.0, "amount": 599324759.49}, {"time": "2026-07-13 13:51:00", "open": 14.14, "high": 14.14, "low": 14.14, "close": 14.14, "volume": 413617.0, "amount": 600522459.5}, {"time": "2026-07-13 13:52:00", "open": 14.14, "high": 14.14, "low": 14.14, "close": 14.14, "volume": 415052.0, "amount": 602550593.51}, {"time": "2026-07-13 13:53:00", "open": 14.18, "high": 14.18, "low": 14.18, "close": 14.18, "volume": 415699.0, "amount": 603466734.51}, {"time": "2026-07-13 13:54:00", "open": 14.19, "high": 14.19, "low": 14.19, "close": 14.19, "volume": 416198.0, "amount": 604174578.52}, {"time": "2026-07-13 13:55:00", "open": 14.14, "high": 14.14, "low": 14.14, "close": 14.14, "volume": 417322.0, "amount": 605765649.53}, {"time": "2026-07-13 13:56:00", "open": 14.13, "high": 14.13, "low": 14.13, "close": 14.13, "volume": 418784.0, "amount": 607831172.54}, {"time": "2026-07-13 13:57:00", "open": 14.15, "high": 14.15, "low": 14.15, "close": 14.15, "volume": 419054.0, "amount": 608212857.54}, {"time": "2026-07-13 13:58:00", "open": 14.12, "high": 14.12, "low": 14.12, "close": 14.12, "volume": 420888.0, "amount": 610802482.55}, {"time": "2026-07-13 13:59:00", "open": 14.11, "high": 14.11, "low": 14.11, "close": 14.11, "volume": 421328.0, "amount": 611423371.56}, {"time": "2026-07-13 14:00:00", "open": 14.14, "high": 14.14, "low": 14.14, "close": 14.14, "volume": 422014.0, "amount": 612392698.56}, {"time": "2026-07-13 14:01:00", "open": 14.13, "high": 14.13, "low": 14.13, "close": 14.13, "volume": 429832.0, "amount": 623417913.62}, {"time": "2026-07-13 14:02:00", "open": 14.12, "high": 14.12, "low": 14.12, "close": 14.12, "volume": 430325.0, "amount": 624114405.62}, {"time": "2026-07-13 14:03:00", "open": 14.11, "high": 14.11, "low": 14.11, "close": 14.11, "volume": 431041.0, "amount": 625124966.63}, {"time": "2026-07-13 14:04:00", "open": 14.1, "high": 14.1, "low": 14.1, "close": 14.1, "volume": 431839.0, "amount": 626251184.63}, {"time": "2026-07-13 14:05:00", "open": 14.09, "high": 14.09, "low": 14.09, "close": 14.09, "volume": 432695.0, "amount": 627457739.64}, {"time": "2026-07-13 14:06:00", "open": 14.1, "high": 14.1, "low": 14.1, "close": 14.1, "volume": 433653.0, "amount": 628808307.65}, {"time": "2026-07-13 14:07:00", "open": 14.08, "high": 14.08, "low": 14.08, "close": 14.08, "volume": 435641.0, "amount": 631608398.66}, {"time": "2026-07-13 14:08:00", "open": 14.07, "high": 14.07, "low": 14.07, "close": 14.07, "volume": 437045.0, "amount": 633584130.67}, {"time": "2026-07-13 14:09:00", "open": 14.07, "high": 14.07, "low": 14.07, "close": 14.07, "volume": 437946.0, "amount": 634852343.68}, {"time": "2026-07-13 14:10:00", "open": 14.06, "high": 14.06, "low": 14.06, "close": 14.06, "volume": 439283.0, "amount": 636732103.69}, {"time": "2026-07-13 14:11:00", "open": 14.07, "high": 14.07, "low": 14.07, "close": 14.07, "volume": 440665.0, "amount": 638675711.7}, {"time": "2026-07-13 14:12:00", "open": 14.06, "high": 14.06, "low": 14.06, "close": 14.06, "volume": 441582.0, "amount": 639965462.71}, {"time": "2026-07-13 14:13:00", "open": 14.07, "high": 14.07, "low": 14.07, "close": 14.07, "volume": 442240.0, "amount": 640890947.71}, {"time": "2026-07-13 14:14:00", "open": 14.07, "high": 14.07, "low": 14.07, "close": 14.07, "volume": 442929.0, "amount": 641860003.72}, {"time": "2026-07-13 14:15:00", "open": 14.06, "high": 14.06, "low": 14.06, "close": 14.06, "volume": 444055.0, "amount": 643443610.73}, {"time": "2026-07-13 14:16:00", "open": 14.08, "high": 14.08, "low": 14.08, "close": 14.08, "volume": 445124.0, "amount": 644947535.74}, {"time": "2026-07-13 14:17:00", "open": 14.07, "high": 14.07, "low": 14.07, "close": 14.07, "volume": 445523.0, "amount": 645508980.74}, {"time": "2026-07-13 14:18:00", "open": 14.08, "high": 14.08, "low": 14.08, "close": 14.08, "volume": 446393.0, "amount": 646733806.75}, {"time": "2026-07-13 14:19:00", "open": 14.12, "high": 14.12, "low": 14.12, "close": 14.12, "volume": 447698.0, "amount": 648574343.76}, {"time": "2026-07-13 14:20:00", "open": 14.09, "high": 14.09, "low": 14.09, "close": 14.09, "volume": 448724.0, "amount": 650020666.76}, {"time": "2026-07-13 14:21:00", "open": 14.09, "high": 14.09, "low": 14.09, "close": 14.09, "volume": 449704.0, "amount": 651402188.77}, {"time": "2026-07-13 14:22:00", "open": 14.08, "high": 14.08, "low": 14.08, "close": 14.08, "volume": 450796.0, "amount": 652939805.78}, {"time": "2026-07-13 14:23:00", "open": 14.08, "high": 14.08, "low": 14.08, "close": 14.08, "volume": 451464.0, "amount": 653880428.78}, {"time": "2026-07-13 14:24:00", "open": 14.08, "high": 14.08, "low": 14.08, "close": 14.08, "volume": 452886.0, "amount": 655880562.79}, {"time": "2026-07-13 14:25:00", "open": 14.08, "high": 14.08, "low": 14.08, "close": 14.08, "volume": 453490.0, "amount": 656730756.8}, {"time": "2026-07-13 14:26:00", "open": 14.09, "high": 14.09, "low": 14.09, "close": 14.09, "volume": 454842.0, "amount": 658633875.81}, {"time": "2026-07-13 14:27:00", "open": 14.11, "high": 14.11, "low": 14.11, "close": 14.11, "volume": 458711.0, "amount": 664086407.83}, {"time": "2026-07-13 14:28:00", "open": 14.1, "high": 14.1, "low": 14.1, "close": 14.1, "volume": 460245.0, "amount": 666247762.84}, {"time": "2026-07-13 14:29:00", "open": 14.09, "high": 14.09, "low": 14.09, "close": 14.09, "volume": 460842.0, "amount": 667088845.85}, {"time": "2026-07-13 14:30:00", "open": 14.1, "high": 14.1, "low": 14.1, "close": 14.1, "volume": 462876.0, "amount": 669952298.86}, {"time": "2026-07-13 14:31:00", "open": 14.07, "high": 14.07, "low": 14.07, "close": 14.07, "volume": 464656.0, "amount": 672457933.87}, {"time": "2026-07-13 14:32:00", "open": 14.06, "high": 14.06, "low": 14.06, "close": 14.06, "volume": 466589.0, "amount": 675179256.89}, {"time": "2026-07-13 14:33:00", "open": 14.07, "high": 14.07, "low": 14.07, "close": 14.07, "volume": 467993.0, "amount": 677154256.9}, {"time": "2026-07-13 14:34:00", "open": 14.04, "high": 14.04, "low": 14.04, "close": 14.04, "volume": 470371.0, "amount": 680496103.91}, {"time": "2026-07-13 14:35:00", "open": 14.07, "high": 14.07, "low": 14.07, "close": 14.07, "volume": 472638.0, "amount": 683679153.93}, {"time": "2026-07-13 14:36:00", "open": 14.1, "high": 14.1, "low": 14.1, "close": 14.1, "volume": 474887.0, "amount": 686847126.94}, {"time": "2026-07-13 14:37:00", "open": 14.12, "high": 14.12, "low": 14.12, "close": 14.12, "volume": 476204.0, "amount": 688705616.95}, {"time": "2026-07-13 14:38:00", "open": 14.09, "high": 14.09, "low": 14.09, "close": 14.09, "volume": 478529.0, "amount": 691983727.96}, {"time": "2026-07-13 14:39:00", "open": 14.08, "high": 14.08, "low": 14.08, "close": 14.08, "volume": 479822.0, "amount": 693805439.97}, {"time": "2026-07-13 14:40:00", "open": 14.09, "high": 14.09, "low": 14.09, "close": 14.09, "volume": 480843.0, "amount": 695243579.98}, {"time": "2026-07-13 14:41:00", "open": 14.06, "high": 14.06, "low": 14.06, "close": 14.06, "volume": 483944.0, "amount": 699609538.0}, {"time": "2026-07-13 14:42:00", "open": 14.04, "high": 14.04, "low": 14.04, "close": 14.04, "volume": 486023.0, "amount": 702529829.01}, {"time": "2026-07-13 14:43:00", "open": 14.06, "high": 14.06, "low": 14.06, "close": 14.06, "volume": 486934.0, "amount": 703810293.02}, {"time": "2026-07-13 14:44:00", "open": 14.09, "high": 14.09, "low": 14.09, "close": 14.09, "volume": 489328.0, "amount": 707182569.03}, {"time": "2026-07-13 14:45:00", "open": 14.11, "high": 14.11, "low": 14.11, "close": 14.11, "volume": 491909.0, "amount": 710822497.05}, {"time": "2026-07-13 14:46:00", "open": 14.11, "high": 14.11, "low": 14.11, "close": 14.11, "volume": 493505.0, "amount": 713075726.06}, {"time": "2026-07-13 14:47:00", "open": 14.11, "high": 14.11, "low": 14.11, "close": 14.11, "volume": 495853.0, "amount": 716388699.07}, {"time": "2026-07-13 14:48:00", "open": 14.13, "high": 14.13, "low": 14.13, "close": 14.13, "volume": 497734.0, "amount": 719045622.08}, {"time": "2026-07-13 14:49:00", "open": 14.11, "high": 14.11, "low": 14.11, "close": 14.11, "volume": 500049.0, "amount": 722314145.09}, {"time": "2026-07-13 14:50:00", "open": 14.11, "high": 14.11, "low": 14.11, "close": 14.11, "volume": 501992.0, "amount": 725055376.1}, {"time": "2026-07-13 14:51:00", "open": 14.07, "high": 14.07, "low": 14.07, "close": 14.07, "volume": 504081.0, "amount": 727999800.11}, {"time": "2026-07-13 14:52:00", "open": 14.07, "high": 14.07, "low": 14.07, "close": 14.07, "volume": 506004.0, "amount": 730705519.12}, {"time": "2026-07-13 14:53:00", "open": 14.06, "high": 14.06, "low": 14.06, "close": 14.06, "volume": 508427.0, "amount": 734112676.14}, {"time": "2026-07-13 14:54:00", "open": 14.05, "high": 14.05, "low": 14.05, "close": 14.05, "volume": 511000.0, "amount": 737728249.63}, {"time": "2026-07-13 14:55:00", "open": 14.04, "high": 14.04, "low": 14.04, "close": 14.04, "volume": 516226.0, "amount": 745063371.76}, {"time": "2026-07-13 14:56:00", "open": 14.05, "high": 14.05, "low": 14.05, "close": 14.05, "volume": 520633.0, "amount": 751255854.86}, {"time": "2026-07-13 14:57:00", "open": 14.05, "high": 14.05, "low": 14.05, "close": 14.05, "volume": 525551.0, "amount": 758164637.98}, {"time": "2026-07-13 14:58:00", "open": 14.05, "high": 14.05, "low": 14.05, "close": 14.05, "volume": 525571.0, "amount": 758192727.98}, {"time": "2026-07-13 14:59:00", "open": 14.05, "high": 14.05, "low": 14.05, "close": 14.05, "volume": 525571.0, "amount": 758193190.0}]}